{"declarations":[{"Sub":"Sub","id":"main","parameters":null,"statements":[{"listanumbers":[],"listanumbersFalse":[],"listasig":[],"IF":"If","expression":{"listanumbers":[],"listanumbersFalse":[],"listasig":[],"Id":null,"lugar":null,"listaverdaderas":[4,7],"listafalsas":[6],"value":null,"operador":"Not","expression1":{"listanumbers":[],"listanumbersFalse":[],"listasig":[],"Id":null,"lugar":"a>b","listaverdaderas":[6],"listafalsas":[4,7],"value":null,"operador":"And","expression1":{"listanumbers":[],"listanumbersFalse":[],"listasig":[],"Id":null,"lugar":"a>b","listaverdaderas":[3],"listafalsas":[4],"expression1":{"listanumbers":[],"listanumbersFalse":[],"listasig":[],"Id":"a","lugar":"a","listaverdaderas":[],"listafalsas":[]},"operador":">","expression2":{"listanumbers":[],"listanumbersFalse":[],"listasig":[],"Id":"b","lugar":"b","listaverdaderas":[],"listafalsas":[]},"lugarFor":null},"expression2":{"listanumbers":[],"listanumbersFalse":[],"listasig":[],"Id":null,"lugar":"b>c","listaverdaderas":[6],"listafalsas":[7],"expression1":{"listanumbers":[],"listanumbersFalse":[],"listasig":[],"Id":"b","lugar":"b","listaverdaderas":[],"listafalsas":[]},"operador":">","expression2":{"listanumbers":[],"listanumbersFalse":[],"listasig":[],"Id":"c","lugar":"c","listaverdaderas":[],"listafalsas":[]},"lugarFor":null}},"expression2":null},"Then":"Then","Else":null,"statements":[{"listanumbers":[],"listanumbersFalse":[],"listasig":[],"IF":"If","expression":{"listanumbers":[],"listanumbersFalse":[],"listasig":[],"Id":null,"lugar":null,"listaverdaderas":[10],"listafalsas":[11],"expression1":{"listanumbers":[],"listanumbersFalse":[],"listasig":[],"Id":"a","lugar":"a","listaverdaderas":[],"listafalsas":[]},"operador":"<","expression2":{"listanumbers":[],"listanumbersFalse":[],"listasig":[],"Id":null,"lugar":"10","listaverdaderas":[],"listafalsas":[],"stringval":null,"number":10},"lugarFor":null},"Then":"Then","Else":null,"statements":[{"listanumbers":[],"listanumbersFalse":[],"listasig":[],"Write":"Write","literalExpression":{"listanumbers":[],"listanumbersFalse":[],"listasig":[],"Id":null,"lugar":"\"If anidado\"","listaverdaderas":[],"listafalsas":[],"stringval":"If anidado","number":null},"Id":null}],"elseIfStatements":null,"elseStatements":null,"endIf":"End IF","etiqueta":null},{"listanumbers":[],"listanumbersFalse":[],"listasig":[],"Write":"Write","literalExpression":{"listanumbers":[],"listanumbersFalse":[],"listasig":[],"Id":null,"lugar":"\"Hola\"","listaverdaderas":[],"listafalsas":[],"stringval":"Hola","number":null},"Id":null}],"elseIfStatements":null,"elseStatements":null,"endIf":"End IF","etiqueta":null},{"listanumbers":[],"listanumbersFalse":[],"listasig":[],"variableDeclarator":{"Dim":"Dim","Id":"c","As":"As","Equals":"=","expression":{"listanumbers":[],"listanumbersFalse":[],"listasig":[],"Id":null,"lugar":"30","listaverdaderas":[],"listafalsas":[],"stringval":null,"number":30},"dataType":"Integer","lugar":"c"},"variableDeclaration":null,"lugar":"c"},{"listanumbers":[],"listanumbersFalse":[],"listasig":[],"variableDeclarator":{"Dim":"Dim","Id":"b","As":"As","Equals":"=","expression":{"listanumbers":[],"listanumbersFalse":[],"listasig":[],"Id":null,"lugar":"20","listaverdaderas":[],"listafalsas":[],"stringval":null,"number":20},"dataType":"Integer","lugar":"b"},"variableDeclaration":null,"lugar":"b"},{"listanumbers":[],"listanumbersFalse":[],"listasig":[],"variableDeclarator":{"Dim":"Dim","Id":"a","As":"As","Equals":"=","expression":{"listanumbers":[],"listanumbersFalse":[],"listasig":[],"Id":null,"lugar":"10","listaverdaderas":[],"listafalsas":[],"stringval":null,"number":10},"dataType":"Integer","lugar":"a"},"variableDeclaration":null,"lugar":"a"}],"endSub":"End Sub"}]}